langchain_datura/__init__.py
langchain_datura/agent.py
langchain_datura/search_tools.py
langchain_datura/tools.py
langchain_datura-0.1.1.dist-info/METADATA
langchain_datura-0.1.1.dist-info/WHEEL
langchain_datura-0.1.1.dist-info/top_level.txt
langchain_datura-0.1.1.dist-info/RECORD
