Metadata-Version: 2.4
Name: langchain-datura
Version: 0.1.1
Summary: LangChain integration with Datura API for search and data-fetching tools.
Home-page: https://github.com/Datura-ai/langchain-datura
Author: Datura
Author-email: Datura <support@datura.ai>
License: MIT
Project-URL: Homepage, https://github.com/Datura-ai/langchain-datura
Classifier: Programming Language :: Python :: 3
Classifier: License :: OSI Approved :: MIT License
Classifier: Operating System :: OS Independent
Requires-Python: >=3.7
Requires-Dist: langchain-core==0.3.51
Requires-Dist: langchain==0.3.23
Requires-Dist: pydantic==2.11.3
Requires-Dist: python-dotenv==1.1.0
Requires-Dist: datura-py==0.0.15
Requires-Dist: pytest==8.3.5
Dynamic: author
Dynamic: home-page
Dynamic: requires-python
